python_licenser/__init__.py
python_licenser/__main__.py
python_licenser/site_packages.py
python_licenser/licenses/__init__.py
python_licenser/licenses/apache_1_1.py
python_licenser/licenses/apache_2_0.py
python_licenser/licenses/bsd_2_clause.py
python_licenser/licenses/bsd_3_clause.py
python_licenser/licenses/gpl_2_0.py
python_licenser/licenses/gpl_3_0.py
python_licenser/licenses/isc.py
python_licenser/licenses/lgpl_2_1.py
python_licenser/licenses/lgpl_3_0.py
python_licenser/licenses/mit.py
python_licenser/licenses/mpl_1_0.py
python_licenser/licenses/mpl_1_1.py
python_licenser/licenses/mpl_2_0.py
python_licenser/licenses/pil.py
python_licenser/licenses/python_2_0.py
python_licenser-2020.7.29.data/data/README.md
python_licenser-2020.7.29.dist-info/LICENSE
python_licenser-2020.7.29.dist-info/METADATA
python_licenser-2020.7.29.dist-info/WHEEL
python_licenser-2020.7.29.dist-info/top_level.txt
python_licenser-2020.7.29.dist-info/RECORD
