Metadata-Version: 2.1
Name: python-licenser
Version: 2020.7.29
Summary: The Python licenser is aimed at distilling down the appropriate license for one or many pip "requirements" files into a single file; it supports Python2.7 and Python3.
Home-page: https://github.com/Brian-Williams/python-licenser
Author: Brian Williams
License: MIT
Keywords: sample setuptools development
Platform: UNKNOWN
Classifier: Development Status :: 3 - Alpha
Classifier: Intended Audience :: Developers
Classifier: Topic :: Software Development :: Libraries
Classifier: License :: OSI Approved :: MIT License
Classifier: Programming Language :: Python :: 2.7
Classifier: Programming Language :: Python :: 3.6
Requires-Dist: requests (==2.23.0)
Requires-Dist: PyYAML (==3.13)
Provides-Extra: dev
Requires-Dist: check-manifest ; extra == 'dev'
Provides-Extra: test
Requires-Dist: coverage ; extra == 'test'
